Metadata-Version: 2.1
Name: autogen-agentchat-um
Version: 0.2.38.2
Summary: Enabling Next-Gen LLM Applications via Multi-Agent Conversation Framework
Home-page: https://github.com/microsoft/autogen
Author: AutoGen
Author-email: autogen@microsoft.com
Classifier: Programming Language :: Python :: 3
Classifier: License :: OSI Approved :: MIT License
Classifier: Operating System :: OS Independent
Requires-Python: >=3.8,<3.13
License-File: LICENSE
License-File: LICENSE-CODE
License-File: LICENSE-CODE-KUBERNETES
Requires-Dist: openai>=1.3
Requires-Dist: diskcache
Requires-Dist: termcolor
Requires-Dist: flaml
Requires-Dist: numpy<2,>=1.17.0
Requires-Dist: python-dotenv
Requires-Dist: tiktoken
Requires-Dist: pydantic!=2.6.0,<3,>=1.10
Requires-Dist: docker
Requires-Dist: packaging
Provides-Extra: anthropic
Requires-Dist: anthropic>=0.23.1; extra == "anthropic"
Provides-Extra: autobuild
Requires-Dist: chromadb; extra == "autobuild"
Requires-Dist: sentence-transformers; extra == "autobuild"
Requires-Dist: huggingface-hub; extra == "autobuild"
Requires-Dist: pysqlite3; extra == "autobuild"
Provides-Extra: bedrock
Requires-Dist: boto3>=1.34.149; extra == "bedrock"
Provides-Extra: blendsearch
Requires-Dist: flaml[blendsearch]; extra == "blendsearch"
Provides-Extra: cerebras
Requires-Dist: cerebras-cloud-sdk>=1.0.0; extra == "cerebras"
Provides-Extra: cohere
Requires-Dist: cohere>=5.5.8; extra == "cohere"
Provides-Extra: cosmosdb
Requires-Dist: azure-cosmos>=4.2.0; extra == "cosmosdb"
Provides-Extra: gemini
Requires-Dist: google-generativeai<1,>=0.5; extra == "gemini"
Requires-Dist: google-cloud-aiplatform; extra == "gemini"
Requires-Dist: google-auth; extra == "gemini"
Requires-Dist: pillow; extra == "gemini"
Requires-Dist: pydantic; extra == "gemini"
Provides-Extra: graph
Requires-Dist: networkx; extra == "graph"
Requires-Dist: matplotlib; extra == "graph"
Provides-Extra: groq
Requires-Dist: groq>=0.9.0; extra == "groq"
Provides-Extra: jupyter-executor
Requires-Dist: jupyter-kernel-gateway; extra == "jupyter-executor"
Requires-Dist: websocket-client; extra == "jupyter-executor"
Requires-Dist: requests; extra == "jupyter-executor"
Requires-Dist: jupyter-client>=8.6.0; extra == "jupyter-executor"
Requires-Dist: ipykernel>=6.29.0; extra == "jupyter-executor"
Provides-Extra: kubernetes
Requires-Dist: kubernetes>=27.2.0; extra == "kubernetes"
Provides-Extra: lmm
Requires-Dist: replicate; extra == "lmm"
Requires-Dist: pillow; extra == "lmm"
Provides-Extra: long-context
Requires-Dist: llmlingua<0.3; extra == "long-context"
Provides-Extra: mathchat
Requires-Dist: sympy; extra == "mathchat"
Requires-Dist: pydantic==1.10.9; extra == "mathchat"
Requires-Dist: wolframalpha; extra == "mathchat"
Provides-Extra: mistral
Requires-Dist: mistralai>=1.0.1; extra == "mistral"
Provides-Extra: ollama
Requires-Dist: ollama>=0.3.3; extra == "ollama"
Requires-Dist: fix-busted-json>=0.0.18; extra == "ollama"
Provides-Extra: redis
Requires-Dist: redis; extra == "redis"
Provides-Extra: retrievechat
Requires-Dist: protobuf==4.25.3; extra == "retrievechat"
Requires-Dist: chromadb; extra == "retrievechat"
Requires-Dist: sentence-transformers; extra == "retrievechat"
Requires-Dist: pypdf; extra == "retrievechat"
Requires-Dist: ipython; extra == "retrievechat"
Requires-Dist: beautifulsoup4; extra == "retrievechat"
Requires-Dist: markdownify; extra == "retrievechat"
Provides-Extra: retrievechat-couchbase
Requires-Dist: protobuf==4.25.3; extra == "retrievechat-couchbase"
Requires-Dist: chromadb; extra == "retrievechat-couchbase"
Requires-Dist: sentence-transformers; extra == "retrievechat-couchbase"
Requires-Dist: pypdf; extra == "retrievechat-couchbase"
Requires-Dist: ipython; extra == "retrievechat-couchbase"
Requires-Dist: beautifulsoup4; extra == "retrievechat-couchbase"
Requires-Dist: markdownify; extra == "retrievechat-couchbase"
Requires-Dist: couchbase>=4.3.0; extra == "retrievechat-couchbase"
Provides-Extra: retrievechat-mongodb
Requires-Dist: protobuf==4.25.3; extra == "retrievechat-mongodb"
Requires-Dist: chromadb; extra == "retrievechat-mongodb"
Requires-Dist: sentence-transformers; extra == "retrievechat-mongodb"
Requires-Dist: pypdf; extra == "retrievechat-mongodb"
Requires-Dist: ipython; extra == "retrievechat-mongodb"
Requires-Dist: beautifulsoup4; extra == "retrievechat-mongodb"
Requires-Dist: markdownify; extra == "retrievechat-mongodb"
Requires-Dist: pymongo>=4.0.0; extra == "retrievechat-mongodb"
Provides-Extra: retrievechat-pgvector
Requires-Dist: protobuf==4.25.3; extra == "retrievechat-pgvector"
Requires-Dist: chromadb; extra == "retrievechat-pgvector"
Requires-Dist: sentence-transformers; extra == "retrievechat-pgvector"
Requires-Dist: pypdf; extra == "retrievechat-pgvector"
Requires-Dist: ipython; extra == "retrievechat-pgvector"
Requires-Dist: beautifulsoup4; extra == "retrievechat-pgvector"
Requires-Dist: markdownify; extra == "retrievechat-pgvector"
Requires-Dist: pgvector>=0.2.5; extra == "retrievechat-pgvector"
Requires-Dist: psycopg[binary]>=3.1.18; extra == "retrievechat-pgvector"
Provides-Extra: retrievechat-qdrant
Requires-Dist: protobuf==4.25.3; extra == "retrievechat-qdrant"
Requires-Dist: chromadb; extra == "retrievechat-qdrant"
Requires-Dist: sentence-transformers; extra == "retrievechat-qdrant"
Requires-Dist: pypdf; extra == "retrievechat-qdrant"
Requires-Dist: ipython; extra == "retrievechat-qdrant"
Requires-Dist: beautifulsoup4; extra == "retrievechat-qdrant"
Requires-Dist: markdownify; extra == "retrievechat-qdrant"
Requires-Dist: qdrant-client; extra == "retrievechat-qdrant"
Requires-Dist: fastembed>=0.3.1; extra == "retrievechat-qdrant"
Provides-Extra: teachable
Requires-Dist: chromadb; extra == "teachable"
Provides-Extra: test
Requires-Dist: ipykernel; extra == "test"
Requires-Dist: nbconvert; extra == "test"
Requires-Dist: nbformat; extra == "test"
Requires-Dist: pre-commit; extra == "test"
Requires-Dist: pytest-cov>=5; extra == "test"
Requires-Dist: pytest-asyncio; extra == "test"
Requires-Dist: pytest<8,>=6.1.1; extra == "test"
Requires-Dist: pandas; extra == "test"
Provides-Extra: together
Requires-Dist: together>=1.2; extra == "together"
Provides-Extra: types
Requires-Dist: mypy==1.9.0; extra == "types"
Requires-Dist: pytest<8,>=6.1.1; extra == "types"
Requires-Dist: jupyter-kernel-gateway; extra == "types"
Requires-Dist: websocket-client; extra == "types"
Requires-Dist: requests; extra == "types"
Requires-Dist: jupyter-client>=8.6.0; extra == "types"
Requires-Dist: ipykernel>=6.29.0; extra == "types"
Provides-Extra: websockets
Requires-Dist: websockets<13,>=12.0; extra == "websockets"
Provides-Extra: websurfer
Requires-Dist: beautifulsoup4; extra == "websurfer"
Requires-Dist: markdownify; extra == "websurfer"
Requires-Dist: pathvalidate; extra == "websurfer"
Requires-Dist: puremagic; extra == "websurfer"
Requires-Dist: pdfminer.six; extra == "websurfer"
Requires-Dist: mammoth; extra == "websurfer"
Requires-Dist: python-pptx; extra == "websurfer"
Requires-Dist: pandas; extra == "websurfer"
Requires-Dist: openpyxl; extra == "websurfer"
Requires-Dist: youtube-transcript-api==0.6.0; extra == "websurfer"
